rmost/__init__.py
rmost/tests.py
rmost-1.2.dist-info/METADATA
rmost-1.2.dist-info/WHEEL
rmost-1.2.dist-info/top_level.txt
rmost-1.2.dist-info/RECORD
