Metadata-Version: 2.1
Name: rmost
Version: 1.2
Summary: no :^
Home-page: UNKNOWN
Author: YarKiy
Author-email: rosya6721@gmail.com
License: UNKNOWN
Platform: UNKNOWN
Classifier: Programming Language :: Python :: 3
Classifier: License :: OSI Approved :: MIT License
Classifier: Operating System :: OS Independent
Requires-Python: >=3.6
